ivan/__init__.py
ivan/cli.py
ivan/plugins/__init__.py
ivan/plugins/cve_compare.py
ivan/plugins/database.py
ivan/plugins/dbconfig.py
ivan/plugins/display.py
ivan/plugins/epss.py
ivan/plugins/export.py
ivan/plugins/find.py
ivan/plugins/ip.py
ivan/plugins/keys.py
ivan/plugins/mail.py
ivan/plugins/push.py
ivan/plugins/query_export.py
ivan/plugins/sc_vuln_export.py
ivan/plugins/scan.py
ivan/plugins/scan_evaluation.py
ivan/plugins/scanidv_vuln_export.py
ivan/plugins/send_mail.py
ivan/plugins/smtp.py
ivan/plugins/software.py
ivan/plugins/ssh.py
ivan/plugins/update.py
ivan_pro-2.0.1.dist-info/METADATA
ivan_pro-2.0.1.dist-info/WHEEL
ivan_pro-2.0.1.dist-info/entry_points.txt
ivan_pro-2.0.1.dist-info/top_level.txt
ivan_pro-2.0.1.dist-info/RECORD
