Metadata-Version: 2.1
Name: ivan-pro
Version: 2.0.1
Summary: A command-line interface to Tenable Security Center
Home-page: https://github.com/packetchaos/ivan
Author: Casey Reid
Author-email: itprofguru@gmail.com
License: GNUv3
Keywords: tenable securitycenter ivan tsc,automation
Platform: UNKNOWN
Classifier: Programming Language :: Python :: 3
Classifier: License :: OSI Approved :: GNU General Public License v3 (GPLv3)
Classifier: Operating System :: OS Independent
Requires-Python: >=3.0
Requires-Dist: Click >=7.0
Requires-Dist: requests >=2.26.0
Requires-Dist: flask >=1.1.1
Requires-Dist: IPy >=1.0
Requires-Dist: pytenable >=1.4.3
Requires-Dist: arrow >=0.17.0
Requires-Dist: typing-extensions >=4.0.1
